ramda/F.py
ramda/T.py
ramda/__init__.py
ramda/add.py
ramda/adjust.py
ramda/all.py
ramda/all_pass.py
ramda/always.py
ramda/and_func.py
ramda/any.py
ramda/any_pass.py
ramda/ap.py
ramda/aperture.py
ramda/append.py
ramda/apply.py
ramda/apply_spec.py
ramda/apply_to.py
ramda/ascend.py
ramda/assoc.py
ramda/assoc_path.py
ramda/binary.py
ramda/bind.py
ramda/both.py
ramda/call.py
ramda/chain.py
ramda/clamp.py
ramda/clone.py
ramda/comparator.py
ramda/complement.py
ramda/compose.py
ramda/concat.py
ramda/cond.py
ramda/cons.py
ramda/contains.py
ramda/contains_with.py
ramda/converge.py
ramda/count_by.py
ramda/curry.py
ramda/curry_n.py
ramda/dec.py
ramda/deep_map.py
ramda/default_to.py
ramda/descend.py
ramda/difference.py
ramda/difference_with.py
ramda/dissoc.py
ramda/dissoc_path.py
ramda/divide.py
ramda/drop.py
ramda/drop_last.py
ramda/drop_last_while.py
ramda/drop_repeats.py
ramda/drop_repeats_with.py
ramda/drop_while.py
ramda/either.py
ramda/empty.py
ramda/ends_with.py
ramda/eq_by.py
ramda/eq_props.py
ramda/equals.py
ramda/evolve.py
ramda/filter.py
ramda/find.py
ramda/find_index.py
ramda/find_last.py
ramda/find_last_index.py
ramda/flatten.py
ramda/flip.py
ramda/for_each.py
ramda/for_each_obj_indexed.py
ramda/from_pairs.py
ramda/getitem.py
ramda/greater.py
ramda/group_by.py
ramda/group_with.py
ramda/gt.py
ramda/gte.py
ramda/has.py
ramda/head.py
ramda/identical.py
ramda/identity.py
ramda/if_else.py
ramda/inc.py
ramda/index_by.py
ramda/index_of.py
ramda/init.py
ramda/inner_join.py
ramda/insert.py
ramda/insert_all.py
ramda/intersection.py
ramda/intersperse.py
ramda/invert.py
ramda/invert_obj.py
ramda/invoker.py
ramda/is_.py
ramda/is_empty.py
ramda/is_nil.py
ramda/join.py
ramda/juxt.py
ramda/keys.py
ramda/last.py
ramda/last_index_of.py
ramda/length.py
ramda/lesser.py
ramda/lt.py
ramda/lte.py
ramda/map.py
ramda/map_accum.py
ramda/map_accum_right.py
ramda/map_obj_indexed.py
ramda/match.py
ramda/max.py
ramda/max_by.py
ramda/mean.py
ramda/median.py
ramda/memoize.py
ramda/memoize_with.py
ramda-0.7.6.dist-info/LICENSE
ramda-0.7.6.dist-info/METADATA
ramda-0.7.6.dist-info/WHEEL
ramda-0.7.6.dist-info/top_level.txt
ramda-0.7.6.dist-info/RECORD
