Metadata-Version: 2.1
Name: ramda
Version: 0.7.6
Summary: Python clone of ramda.js (ramdajs.com)
Home-page: http://github.com/slavaGanzin/ramda.py
Author: Slava Ganzin
Author-email: slava.ganzin@gmail.com
License-File: LICENSE
